geodjango_tigerleaflet-0.2.1.dist-info/DESCRIPTION.rst
geodjango_tigerleaflet-0.2.1.dist-info/METADATA
geodjango_tigerleaflet-0.2.1.dist-info/RECORD
geodjango_tigerleaflet-0.2.1.dist-info/WHEEL
geodjango_tigerleaflet-0.2.1.dist-info/metadata.json
geodjango_tigerleaflet-0.2.1.dist-info/top_level.txt
tigerleaflet/__init__.py
tigerleaflet/admin.py
tigerleaflet/apps.py
tigerleaflet/models.py
tigerleaflet/urls.py
tigerleaflet/views.py
tigerleaflet/management/__init__.py
tigerleaflet/management/commands/__init__.py
tigerleaflet/management/commands/load_counties.py
tigerleaflet/management/commands/load_states.py
tigerleaflet/management/commands/load_tigerleaflet.py
tigerleaflet/migrations/0001_initial.py
tigerleaflet/migrations/__init__.py
tigerleaflet/static/css/tigerleaflet.css
tigerleaflet/static/js/jquery.min.js
tigerleaflet/static/js/tigerleaflet.js
tigerleaflet/templates/tigerleaflet-base.html
tigerleaflet/templates/tigerleaflet_country.html
tigerleaflet/templates/tigerleaflet_county.html
tigerleaflet/templates/tigerleaflet_init.html
tigerleaflet/templates/tigerleaflet_state.html
tigerleaflet/templates/pages/county.html
tigerleaflet/templates/pages/index.html
tigerleaflet/templates/pages/state.html
tigerleaflet/templatetags/__init__.py
tigerleaflet/templatetags/tigerleaflet_tags.py
