Metadata-Version: 2.0
Name: geodjango-tigerleaflet
Version: 0.2.1
Summary: Leaflet for Geodjango with US TIGER State and County data
Home-page: https://github.com/jlillest/geodjango-tigerleaflet
Author: Jon Lillestolen
Author-email: jlillest@gmail.com
License: MIT
Keywords: Leaflet for Geodjango with US TIGER State and County data
Platform: UNKNOWN
Classifier: Development Status :: 3 - Alpha
Classifier: Framework :: Django
Classifier: Framework :: Django :: 1.10
Classifier: Intended Audience :: Developers
Classifier: License :: OSI Approved :: BSD License
Classifier: Natural Language :: English
Classifier: Programming Language :: Python :: 3
Classifier: Programming Language :: Python :: 3.4
Classifier: Programming Language :: Python :: 3.5
Requires-Dist: django-model-utils (>=2.0)
